odoo/addons/stock_picking_batch_invoice_frequency/README.rst
odoo/addons/stock_picking_batch_invoice_frequency/__init__.py
odoo/addons/stock_picking_batch_invoice_frequency/__manifest__.py
odoo/addons/stock_picking_batch_invoice_frequency/i18n/es.po
odoo/addons/stock_picking_batch_invoice_frequency/i18n/it.po
odoo/addons/stock_picking_batch_invoice_frequency/i18n/pt_BR.po
odoo/addons/stock_picking_batch_invoice_frequency/i18n/stock_picking_batch_invoice_frequency.pot
odoo/addons/stock_picking_batch_invoice_frequency/models/__init__.py
odoo/addons/stock_picking_batch_invoice_frequency/models/sale_invoice_frequency.py
odoo/addons/stock_picking_batch_invoice_frequency/models/stock_picking.py
odoo/addons/stock_picking_batch_invoice_frequency/models/stock_picking_batch.py
odoo/addons/stock_picking_batch_invoice_frequency/readme/CONFIGURE.md
odoo/addons/stock_picking_batch_invoice_frequency/readme/CONTRIBUTORS.md
odoo/addons/stock_picking_batch_invoice_frequency/readme/DESCRIPTION.md
odoo/addons/stock_picking_batch_invoice_frequency/readme/USAGE.md
odoo/addons/stock_picking_batch_invoice_frequency/static/description/icon.png
odoo/addons/stock_picking_batch_invoice_frequency/static/description/index.html
odoo/addons/stock_picking_batch_invoice_frequency/tests/__init__.py
odoo/addons/stock_picking_batch_invoice_frequency/tests/test_batch_invoice.py
odoo/addons/stock_picking_batch_invoice_frequency/views/sale_invoice_frequency.xml
odoo_addon_stock_picking_batch_invoice_frequency-18.0.1.0.1.1.dist-info/METADATA
odoo_addon_stock_picking_batch_invoice_frequency-18.0.1.0.1.1.dist-info/WHEEL
odoo_addon_stock_picking_batch_invoice_frequency-18.0.1.0.1.1.dist-info/top_level.txt
odoo_addon_stock_picking_batch_invoice_frequency-18.0.1.0.1.1.dist-info/RECORD
