Metadata-Version: 2.1
Name: odoo-addon-stock_picking_batch_invoice_frequency
Version: 18.0.1.0.1.1
Requires-Python: >=3.10
Requires-Dist: odoo-addon-sale_invoice_frequency==18.0.*
Requires-Dist: odoo==18.0.*
Summary: Invoice Sale Orders from Stock Pickin Batch
Home-page: https://github.com/OCA/stock-logistics-workflow
License: AGPL-3
Author: Moduon, Odoo Community Association (OCA)
Author-email: support@odoo-community.org
Classifier: Programming Language :: Python
Classifier: Framework :: Odoo
Classifier: Framework :: Odoo :: 18.0
Classifier: License :: OSI Approved :: GNU Affero General Public License v3
Classifier: Development Status :: 3 - Alpha
